{
  "_fv": 24,
  "_type": "recipe",
  "definition": {
    "recipeType": "Crafting",
    "xpReward": 0.0,
    "cookingTime": 200,
    "recipeRetstackSize": 1,
    "recipeShapeless": false,
    "recipeSlots": [
      {
        "value": ""
      },
      {
        "value": "CUSTOM:Onedollar"
      },
      {
        "value": ""
      },
      {
        "value": "CUSTOM:Onedollar"
      },
      {
        "value": "Items.EGG"
      },
      {
        "value": "CUSTOM:Onedollar"
      },
      {
        "value": ""
      },
      {
        "value": "CUSTOM:Onedollar"
      },
      {
        "value": ""
      }
    ],
    "recipeReturnStack": {
      "value": "CUSTOM:Madbuck"
    },
    "smeltingInputStack": {
      "value": ""
    },
    "smeltingReturnStack": {
      "value": ""
    },
    "name": "madbuckrec",
    "namespace": "mod"
  }
}